pystdf/BinSummarizer.py
pystdf/IO.py
pystdf/Importer.py
pystdf/Indexing.py
pystdf/Mapping.py
pystdf/OoHelpers.py
pystdf/ParametricSummarizer.py
pystdf/PartSummarizer.py
pystdf/Pipeline.py
pystdf/SummaryStatistics.py
pystdf/TableTemplate.py
pystdf/TestSummarizer.py
pystdf/Types.py
pystdf/V4.py
pystdf/Writers.py
pystdf/__init__.py
pystdf/logexcept.py
pystdf/scripts/__init__.py
pystdf/scripts/rec_index.py
pystdf/scripts/stdf2excel.py
pystdf/scripts/stdf2text.py
pystdf/scripts/stdf2xml.py
pystdf/scripts/stdf_slice.py
pystdf-1.3.4.dist-info/METADATA
pystdf-1.3.4.dist-info/WHEEL
pystdf-1.3.4.dist-info/entry_points.txt
pystdf-1.3.4.dist-info/licenses/LICENSE.txt
pystdf-1.3.4.dist-info/RECORD
