Metadata-Version: 2.1
Name: pystdf
Version: 1.3.4
Summary: Python module for working with STDF files
Author-email: Casey Marshall <casey.marshall@gmail.com>
License-File: LICENSE.txt
Classifier: Development Status :: 4 - Beta
Classifier: Environment :: Console
Classifier: Intended Audience :: Manufacturing
Classifier: License :: Free for non-commercial use
Classifier: License :: OSI Approved :: GNU General Public License (GPL)
Classifier: Operating System :: OS Independent
Classifier: Programming Language :: Python
Classifier: Topic :: Scientific/Engineering :: Electronic Design Automation (EDA)
Classifier: Topic :: Software Development :: Libraries :: Python Modules
Classifier: Topic :: Software Development :: Pre-processors
Classifier: Topic :: Utilities
Requires-Dist: numpy
Requires-Dist: openpyxl
Requires-Dist: pandas
